{
    "texturePath": "assets/sprites.png",
    "sprites": [
        {
            "name": "BIRD_YELLOW",
            "x": 259,
            "y": 679,
            "w": 22,
            "h": 15,
            "totalFrames": 3
        },{
            "name": "BIRD_RED",
            "x": 259,
            "y": 695,
            "w": 22,
            "h": 15,
            "totalFrames": 3
        },{
            "name": "BIRD_BLUE",
            "x": 259,
            "y": 711,
            "w": 22,
            "h": 15,
            "totalFrames": 3
        },{
            "name": "BIRD_GREEN",
            "x": 259,
            "y": 727,
            "w": 22,
            "h": 15,
            "totalFrames": 3
        },{
            "name": "BIRD_PURPLE",
            "x": 259,
            "y": 743,
            "w": 22,
            "h": 15,
            "totalFrames": 3
        },{
            "name": "PIPE_TOP",
            "x": 302,
            "y": 0,
            "w": 26,
            "h": 135,
            "totalFrames": 1
        },{
            "name": "PIPE_BOTTOM",
            "x": 330,
            "y": 0,
            "w": 26,
            "h": 121,
            "totalFrames": 1
        },{
            "name": "COIN",
            "x": 302,
            "y": 137,
            "w": 22,
            "h": 22,
            "totalFrames": 1
        },{
            "name": "TITLE_MENU",
            "x": 146,
            "y": 173,
            "w": 96,
            "h": 22,
            "totalFrames": 1
        },{
            "name": "TITLE_GAME_OVER",
            "x": 146,
            "y": 199,
            "w": 94,
            "h": 19,
            "totalFrames": 1
        },{
            "name": "BTN_MENU",
            "x": 245,
            "y": 118,
            "w": 40,
            "h": 14,
            "totalFrames": 1
        },{
            "name": "BTN_OK",
            "x": 245,
            "y": 134,
            "w": 40,
            "h": 14,
            "totalFrames": 1
        },{
            "name": "BTN_START",
            "x": 241,
            "y": 213,
            "w": 40,
            "h": 14,
            "totalFrames": 1
        },{
            "name": "GAME_MODE",
            "x": 0,
            "y": 0,
            "w": 91,
            "h": 43,
            "totalFrames": 2
        },{
            "name": "BACKGROUND_MENU",
            "x": 0,
            "y": 384,
            "w": 256,
            "h": 192,
            "totalFrames": 2
        },{
            "name": "CLOUD_DAY",
            "x": 0,
            "y": 0,
            "w": 256,
            "h": 92,
            "totalFrames": 2
        },{
            "name": "CLOUD_NIGHT",
            "x": 0,
            "y": 93,
            "w": 256,
            "h": 92,
            "totalFrames": 2
        },{
            "name": "BUILDING_DAY",
            "x": 0,
            "y": 192,
            "w": 256,
            "h": 56,
            "totalFrames": 2
        },{
            "name": "BUILDING_NIGHT",
            "x": 0,
            "y": 254,
            "w": 256,
            "h": 56,
            "totalFrames": 2
        },{
            "name": "GRASS_DAY",
            "x": 0,
            "y": 576,
            "w": 256,
            "h": 50,
            "totalFrames": 2
        },{
            "name": "GRASS_NIGHT",
            "x": 0,
            "y": 626,
            "w": 256,
            "h": 50,
            "totalFrames": 2
        }
    ]
}